[{"file": "f1/fruits1f.png", "new_label": "True"}, {"file": "f1/fruits1.png", "new_label": "False"}, {"file": "f1/fruits1b.png", "new_label": "True"}, {"file": "f1/fruits1c.png", "new_label": "True"}, {"file": "f1/fruits1d.png", "new_label": "True"}, {"file": "f1/fruits1e.png", "new_label": "True"}, {"file": "f2/fruits2.png", "new_label": "False"}, {"file": "f2/fruits2f.png", "new_label": "False"}, {"file": "f2/fruits2d.png", "new_label": "False"}, {"file": "f2/fruits2e.png", "new_label": "False"}, {"file": "f2/fruits2b.png", "new_label": "False"}, {"file": "f2/fruits2c.png", "new_label": "False"}]
